generic_cli_base/__init__.py
generic_cli_base-0.1.0.dist-info/LICENSE
generic_cli_base-0.1.0.dist-info/WHEEL
generic_cli_base-0.1.0.dist-info/METADATA
generic_cli_base-0.1.0.dist-info/RECORD
