Metadata-Version: 2.1
Name: generic-cli-base
Version: 0.1.0
Summary: A simple Commandline Application Base
License: MIT
Author: Mark Hall
Author-email: mark.hall@work.room3b.eu
Requires-Python: >=3.10,<4.0
Classifier: License :: OSI Approved :: MIT License
Classifier: Programming Language :: Python :: 3
Classifier: Programming Language :: Python :: 3.10
Requires-Dist: Cerberus (>=1.3.4,<2.0.0)
Requires-Dist: PyYAML (>=6.0,<7.0)
Requires-Dist: click (>=8.1.3,<9.0.0)
